{
    "CONNECTIONS": [
        [
            "[T] props_002_modeling.Output", 
            "[F] props_002_modeling_001 | ma.Input"
        ], 
        [
            "[T] props_002_modeling.Output", 
            "[F] props_002_modeling_001 | blend.Input"
        ], 
        [
            "[E] props_002.Output", 
            "[T] props_002_lookdev.Input"
        ], 
        [
            "[E] props_002.Output", 
            "[T] props_002_groom.Input"
        ], 
        [
            "[E] props_002.Output", 
            "[T] props_002_rigging.Input"
        ], 
        [
            "[T] props_002_modeling.Output", 
            "[F] props_002_modeling_001 | png.Input"
        ], 
        [
            "[E] props_002.Output", 
            "[T] props_002_modeling.Input"
        ]
    ], 
    "NODES": {
        "[E] props_002": {
            "alternate": true, 
            "attributes": [
                {
                    "dataType": "<type 'str'>", 
                    "name": "Input", 
                    "plug": false, 
                    "preset": "attr_preset_1", 
                    "socket": true
                }, 
                {
                    "dataType": "<type 'str'>", 
                    "name": "Output", 
                    "plug": true, 
                    "preset": "attr_preset_1", 
                    "socket": false
                }
            ], 
            "position": [
                86.2508018867926, 
                1005.6562735849054
            ], 
            "preset": "node_preset_1"
        }, 
        "[F] props_002_modeling_001 | blend": {
            "alternate": true, 
            "attributes": [
                {
                    "dataType": "<type 'str'>", 
                    "name": "Input", 
                    "plug": false, 
                    "preset": "attr_preset_1", 
                    "socket": true
                }, 
                {
                    "dataType": "<type 'str'>", 
                    "name": "Output", 
                    "plug": true, 
                    "preset": "attr_preset_1", 
                    "socket": false
                }
            ], 
            "position": [
                771.8019811320748, 
                909.157735849056
            ], 
            "preset": "node_preset_2"
        }, 
        "[F] props_002_modeling_001 | ma": {
            "alternate": true, 
            "attributes": [
                {
                    "dataType": "<type 'str'>", 
                    "name": "Input", 
                    "plug": false, 
                    "preset": "attr_preset_1", 
                    "socket": true
                }, 
                {
                    "dataType": "<type 'str'>", 
                    "name": "Output", 
                    "plug": true, 
                    "preset": "attr_preset_1", 
                    "socket": false
                }
            ], 
            "position": [
                778.5392452830183, 
                1061.4199056603768
            ], 
            "preset": "node_preset_2"
        }, 
        "[F] props_002_modeling_001 | png": {
            "alternate": true, 
            "attributes": [
                {
                    "dataType": "<type 'str'>", 
                    "name": "Input", 
                    "plug": false, 
                    "preset": "attr_preset_1", 
                    "socket": true
                }, 
                {
                    "dataType": "<type 'str'>", 
                    "name": "Output", 
                    "plug": true, 
                    "preset": "attr_preset_1", 
                    "socket": false
                }
            ], 
            "position": [
                772.7125471698116, 
                755.193867924528
            ], 
            "preset": "node_preset_2"
        }, 
        "[T] props_002_groom": {
            "alternate": true, 
            "attributes": [
                {
                    "dataType": "<type 'str'>", 
                    "name": "Input", 
                    "plug": false, 
                    "preset": "attr_preset_1", 
                    "socket": true
                }, 
                {
                    "dataType": "<type 'str'>", 
                    "name": "Output", 
                    "plug": true, 
                    "preset": "attr_preset_1", 
                    "socket": false
                }
            ], 
            "position": [
                461.63830188679253, 
                1206.1712735849057
            ], 
            "preset": "node_preset_3"
        }, 
        "[T] props_002_lookdev": {
            "alternate": true, 
            "attributes": [
                {
                    "dataType": "<type 'str'>", 
                    "name": "Input", 
                    "plug": false, 
                    "preset": "attr_preset_1", 
                    "socket": true
                }, 
                {
                    "dataType": "<type 'str'>", 
                    "name": "Output", 
                    "plug": true, 
                    "preset": "attr_preset_1", 
                    "socket": false
                }
            ], 
            "position": [
                468.2508018867927, 
                1358.2587735849054
            ], 
            "preset": "node_preset_3"
        }, 
        "[T] props_002_modeling": {
            "alternate": true, 
            "attributes": [
                {
                    "dataType": "<type 'str'>", 
                    "name": "Input", 
                    "plug": false, 
                    "preset": "attr_preset_1", 
                    "socket": true
                }, 
                {
                    "dataType": "<type 'str'>", 
                    "name": "Output", 
                    "plug": true, 
                    "preset": "attr_preset_1", 
                    "socket": false
                }
            ], 
            "position": [
                463.91070754717, 
                842.6151415094339
            ], 
            "preset": "node_preset_3"
        }, 
        "[T] props_002_rigging": {
            "alternate": true, 
            "attributes": [
                {
                    "dataType": "<type 'str'>", 
                    "name": "Input", 
                    "plug": false, 
                    "preset": "attr_preset_1", 
                    "socket": true
                }, 
                {
                    "dataType": "<type 'str'>", 
                    "name": "Output", 
                    "plug": true, 
                    "preset": "attr_preset_1", 
                    "socket": false
                }
            ], 
            "position": [
                463.8358490566038, 
                1030.886273584906
            ], 
            "preset": "node_preset_3"
        }
    }
}